Graph_State_Machine/__init__.py
Graph_State_Machine/graph.py
Graph_State_Machine/gsm.py
Graph_State_Machine/scanners.py
Graph_State_Machine/scores.py
Graph_State_Machine/selectors.py
Graph_State_Machine/types.py
Graph_State_Machine/updaters.py
Graph_State_Machine/Util/__init__.py
Graph_State_Machine/Util/generic_util.py
Graph_State_Machine/Util/misc.py
Tests/__init__.py
Tests/self_contained_showcase.py
Tests/self_contained_showcase_dict_state.py
Tests/self_contained_showcase_nec_suff.py
Tests/test_examples.py
Graph_State_Machine-3.2.dist-info/LICENSE
Graph_State_Machine-3.2.dist-info/METADATA
Graph_State_Machine-3.2.dist-info/WHEEL
Graph_State_Machine-3.2.dist-info/top_level.txt
Graph_State_Machine-3.2.dist-info/RECORD
