Metadata-Version: 2.1
Name: Graph-State-Machine
Version: 3.2
Summary: A simple library to build easily interpretable computational constructs similar to a Turing machine over a graph, where states are combinations of a graph's (typed) nodes; an example use would be a transparent backend logic which navigates an ontology
Home-page: https://github.com/T-Flet/Graph-State-Machine
Author: Thomas Fletcher
Author-email: T-Fletcher@outlook.com
License: BSD 3-Clause
Classifier: Development Status :: 5 - Production/Stable
Classifier: Programming Language :: Python
Classifier: Programming Language :: Python :: 3.8
Classifier: Programming Language :: Python :: 3.9
Classifier: Programming Language :: Python :: 3.10
Classifier: Programming Language :: Python :: 3.11
Classifier: Programming Language :: Python :: 3.12
License-File: LICENSE
Requires-Dist: networkx >=2.5
Requires-Dist: pandas >=1.1.1
Requires-Dist: matplotlib >=3.3.2
Requires-Dist: plotly >=5.1.0
